decodify/__init__.py
decodify/cli.py
decodify/decodify.py
decodify/algorithms/__init__.py
decodify/algorithms/base64.py
decodify/algorithms/binary.py
decodify/algorithms/hex.py
decodify/algorithms/morse.py
decodify/algorithms/url.py
decodify-0.1.3.dist-info/METADATA
decodify-0.1.3.dist-info/WHEEL
decodify-0.1.3.dist-info/entry_points.txt
decodify-0.1.3.dist-info/top_level.txt
decodify-0.1.3.dist-info/RECORD
