Metadata-Version: 2.2
Name: decodify
Version: 0.1.3
Summary: An advanced package to detect encoding algorithms and decode messages.
Home-page: https://github.com/ishanoshada/decodify
Author: Ishan Oshada
Author-email: ishan.kodithuwakku.offical@gmail.com
Keywords: encoding,decoding,cryptography,cipher,decode,encoder,decoder,base64,hash
Classifier: Programming Language :: Python :: 3
Classifier: Programming Language :: Python :: 3.6
Classifier: Programming Language :: Python :: 3.7
Classifier: Programming Language :: Python :: 3.8
Classifier: Programming Language :: Python :: 3.9
Classifier: License :: OSI Approved :: MIT License
Classifier: Operating System :: OS Independent
Classifier: Topic :: Security :: Cryptography
Classifier: Topic :: Software Development :: Libraries :: Python Modules
Classifier: Intended Audience :: Developers
Classifier: Development Status :: 4 - Beta
Dynamic: author
Dynamic: author-email
Dynamic: classifier
Dynamic: description
Dynamic: description-content-type
Dynamic: home-page
Dynamic: keywords
Dynamic: summary
